{
    "asset": {
        "format": "jpeg",
        "id": "2c7a82f4c31e6a05566f6c026be886ed",
        "name": "images-1.jpeg",
        "path": "file:/Users/Tom/PycharmProjects/Spot/Images/images-1.jpeg",
        "size": {
            "width": 300,
            "height": 168
        },
        "state": 2,
        "type": 1
    },
    "regions": [
        {
            "id": "uZ1jk45lv",
            "type": "RECTANGLE",
            "tags": [
                "UGV"
            ],
            "boundingBox": {
                "height": 102.2912618728807,
                "width": 198.09715634300596,
                "left": 29.028535136031316,
                "top": 47.35408157367448
            },
            "points": [
                {
                    "x": 29.028535136031316,
                    "y": 47.35408157367448
                },
                {
                    "x": 227.12569147903727,
                    "y": 47.35408157367448
                },
                {
                    "x": 227.12569147903727,
                    "y": 149.6453434465552
                },
                {
                    "x": 29.028535136031316,
                    "y": 149.6453434465552
                }
            ]
        }
    ],
    "version": "2.2.0"
}