{
    "asset": {
        "format": "jpeg",
        "id": "6bca4153d89630f58476bd114a37d996",
        "name": "images-85%20copy.jpeg",
        "path": "file:/Users/Tom/PycharmProjects/Spot/Images/images-85%20copy.jpeg",
        "size": {
            "width": 275,
            "height": 183
        },
        "state": 2,
        "type": 1
    },
    "regions": [
        {
            "id": "FfpbIXEtk",
            "type": "RECTANGLE",
            "tags": [
                "UAS"
            ],
            "boundingBox": {
                "height": 112.43395703593002,
                "width": 196.64849187362964,
                "left": 45.15281477184012,
                "top": 38.65944371817592
            },
            "points": [
                {
                    "x": 45.15281477184012,
                    "y": 38.65944371817592
                },
                {
                    "x": 241.80130664546977,
                    "y": 38.65944371817592
                },
                {
                    "x": 241.80130664546977,
                    "y": 151.09340075410594
                },
                {
                    "x": 45.15281477184012,
                    "y": 151.09340075410594
                }
            ]
        }
    ],
    "version": "2.2.0"
}