{
    "asset": {
        "format": "jpeg",
        "id": "849942e48bd8babcb4255d7bfdc2115e",
        "name": "Unknown-72.jpeg",
        "path": "file:/Users/Tom/PycharmProjects/Spot/Images/Unknown-72.jpeg",
        "size": {
            "width": 287,
            "height": 175
        },
        "state": 2,
        "type": 1
    },
    "regions": [
        {
            "id": "FXDcoZxMO",
            "type": "RECTANGLE",
            "tags": [
                "Car"
            ],
            "boundingBox": {
                "height": 123.10131996012784,
                "width": 233.8172927084845,
                "left": 28.51448696833277,
                "top": 26.40777562072031
            },
            "points": [
                {
                    "x": 28.51448696833277,
                    "y": 26.40777562072031
                },
                {
                    "x": 262.3317796768173,
                    "y": 26.40777562072031
                },
                {
                    "x": 262.3317796768173,
                    "y": 149.50909558084814
                },
                {
                    "x": 28.51448696833277,
                    "y": 149.50909558084814
                }
            ]
        }
    ],
    "version": "2.2.0"
}