{
    "asset": {
        "format": "jpeg",
        "id": "a0cdadf94eb07b749bbf110b87a4cb0d",
        "name": "images-111%20copy.jpeg",
        "path": "file:/Users/Tom/PycharmProjects/Spot/Images/images-111%20copy.jpeg",
        "size": {
            "width": 250,
            "height": 167
        },
        "state": 2,
        "type": 1
    },
    "regions": [
        {
            "id": "-gKccIX4T",
            "type": "RECTANGLE",
            "tags": [
                "UAS"
            ],
            "boundingBox": {
                "height": 34.088647385468995,
                "width": 76.34861870323788,
                "left": 30.307860320320565,
                "top": 35.27755048654548
            },
            "points": [
                {
                    "x": 30.307860320320565,
                    "y": 35.27755048654548
                },
                {
                    "x": 106.65647902355845,
                    "y": 35.27755048654548
                },
                {
                    "x": 106.65647902355845,
                    "y": 69.36619787201447
                },
                {
                    "x": 30.307860320320565,
                    "y": 69.36619787201447
                }
            ]
        }
    ],
    "version": "2.2.0"
}