{
    "asset": {
        "format": "jpeg",
        "id": "b478d057f9f74c0604dacb0eeef8ebbd",
        "name": "images-48%20copy.jpeg",
        "path": "file:/Users/Tom/PycharmProjects/Spot/Images/images-48%20copy.jpeg",
        "size": {
            "width": 271,
            "height": 186
        },
        "state": 2,
        "type": 1
    },
    "regions": [
        {
            "id": "pLngFPI8t",
            "type": "RECTANGLE",
            "tags": [
                "UAS"
            ],
            "boundingBox": {
                "height": 41.66962157423123,
                "width": 71.17946312441464,
                "left": 168.1078722769754,
                "top": 78.77314070924022
            },
            "points": [
                {
                    "x": 168.1078722769754,
                    "y": 78.77314070924022
                },
                {
                    "x": 239.28733540139004,
                    "y": 78.77314070924022
                },
                {
                    "x": 239.28733540139004,
                    "y": 120.44276228347144
                },
                {
                    "x": 168.1078722769754,
                    "y": 120.44276228347144
                }
            ]
        },
        {
            "id": "D5Pu55jhC",
            "type": "RECTANGLE",
            "tags": [
                "Person"
            ],
            "boundingBox": {
                "height": 185.95365588885906,
                "width": 120.29038055598387,
                "left": 0,
                "top": 0
            },
            "points": [
                {
                    "x": 0,
                    "y": 0
                },
                {
                    "x": 120.29038055598389,
                    "y": 0
                },
                {
                    "x": 120.29038055598389,
                    "y": 185.9536558888591
                },
                {
                    "x": 0,
                    "y": 185.9536558888591
                }
            ]
        }
    ],
    "version": "2.2.0"
}