{
    "asset": {
        "format": "jpeg",
        "id": "efabf743de853a8eb59419100b7866f1",
        "name": "images-33%20copy.jpeg",
        "path": "file:/Users/Tom/PycharmProjects/Spot/Images/images-33%20copy.jpeg",
        "size": {
            "width": 259,
            "height": 194
        },
        "state": 2,
        "type": 1
    },
    "regions": [
        {
            "id": "MmDOlrU_w",
            "type": "RECTANGLE",
            "tags": [
                "UAS"
            ],
            "boundingBox": {
                "height": 50.498733730683966,
                "width": 97.63793957910056,
                "left": 53.33821186266448,
                "top": 103.97215552632144
            },
            "points": [
                {
                    "x": 53.33821186266448,
                    "y": 103.97215552632144
                },
                {
                    "x": 150.97615144176504,
                    "y": 103.97215552632144
                },
                {
                    "x": 150.97615144176504,
                    "y": 154.4708892570054
                },
                {
                    "x": 53.33821186266448,
                    "y": 154.4708892570054
                }
            ]
        },
        {
            "id": "SasOxN7bc",
            "type": "RECTANGLE",
            "tags": [
                "Person"
            ],
            "boundingBox": {
                "height": 66.88061464588175,
                "width": 23.687883217637385,
                "left": 141.87179203249968,
                "top": 86.08140181444236
            },
            "points": [
                {
                    "x": 141.87179203249968,
                    "y": 86.08140181444236
                },
                {
                    "x": 165.55967525013708,
                    "y": 86.08140181444236
                },
                {
                    "x": 165.55967525013708,
                    "y": 152.96201646032412
                },
                {
                    "x": 141.87179203249968,
                    "y": 152.96201646032412
                }
            ]
        }
    ],
    "version": "2.2.0"
}